sumitomo_f70/__init__.py
sumitomo_f70/sumitomo_f70.py
sumitomo_f70-1.0.0.dist-info/LICENSE.md
sumitomo_f70-1.0.0.dist-info/METADATA
sumitomo_f70-1.0.0.dist-info/WHEEL
sumitomo_f70-1.0.0.dist-info/top_level.txt
sumitomo_f70-1.0.0.dist-info/RECORD
